llm_change_agent/__init__.py
llm_change_agent/cli.py
llm_change_agent/config/llm_config.py
llm_change_agent/constants.py
llm_change_agent/evaluations/__init__.py
llm_change_agent/evaluations/evaluator.py
llm_change_agent/evaluations/input/.keep
llm_change_agent/evaluations/input/eval_docs/EnvironmentOntology_envo.yaml
llm_change_agent/evaluations/input/eval_docs/geneontology_go_ontology.yaml
llm_change_agent/evaluations/input/eval_docs/monarch_initiative_mondo.yaml
llm_change_agent/evaluations/input/eval_docs/obophenotype_cell_ontology.yaml
llm_change_agent/evaluations/input/eval_docs/obophenotype_uberon.yaml
llm_change_agent/evaluations/input/eval_docs/pato_ontology_pato.yaml
llm_change_agent/evaluations/input/evaluation_prs.yaml
llm_change_agent/evaluations/input/expected/EnvironmentOntology_envo.yaml
llm_change_agent/evaluations/input/expected/geneontology_go_ontology.yaml
llm_change_agent/evaluations/input/expected/monarch_initiative_mondo.yaml
llm_change_agent/evaluations/input/expected/obophenotype_cell_ontology.yaml
llm_change_agent/evaluations/input/expected/obophenotype_uberon.yaml
llm_change_agent/evaluations/input/expected/pato_ontology_pato.yaml
llm_change_agent/evaluations/output/cborg/anthropic_claude-sonnet/EnvironmentOntology_envo.yaml
llm_change_agent/evaluations/output/cborg/anthropic_claude-sonnet/geneontology_go_ontology.yaml
llm_change_agent/evaluations/output/cborg/anthropic_claude-sonnet/monarch_initiative_mondo.yaml
llm_change_agent/evaluations/output/cborg/anthropic_claude-sonnet/obophenotype_cell_ontology.yaml
llm_change_agent/evaluations/output/cborg/anthropic_claude-sonnet/obophenotype_uberon.yaml
llm_change_agent/evaluations/output/cborg/anthropic_claude-sonnet/pato_ontology_pato.yaml
llm_change_agent/evaluations/output/cborg/google_gemini-pro/EnvironmentOntology_envo.yaml
llm_change_agent/evaluations/output/cborg/google_gemini-pro/geneontology_go_ontology.yaml
llm_change_agent-0.0.9.dist-info/LICENSE
llm_change_agent-0.0.9.dist-info/METADATA
llm_change_agent-0.0.9.dist-info/WHEEL
llm_change_agent-0.0.9.dist-info/entry_points.txt
llm_change_agent-0.0.9.dist-info/RECORD
