Metadata-Version: 2.1
Name: llm-change-agent
Version: 0.0.9
Summary: llm-change-agent
License: MIT
Author: Harshad Hegde
Author-email: hhegde@lbl.gov
Requires-Python: >=3.9,<4.0
Classifier: License :: OSI Approved :: MIT License
Classifier: Programming Language :: Python :: 3
Classifier: Programming Language :: Python :: 3.9
Classifier: Programming Language :: Python :: 3.10
Classifier: Programming Language :: Python :: 3.11
Classifier: Programming Language :: Python :: 3.12
Requires-Dist: click
Requires-Dist: curies (>=0.7.10,<0.8.0)
Requires-Dist: importlib-metadata (>=8.2.0)
Requires-Dist: kgcl-schema (>=0.6.8,<0.7.0)
Requires-Dist: langchain (>=0.2.12,<0.3.0)
Requires-Dist: langchain-anthropic (>=0.1.22,<0.2.0)
Requires-Dist: langchain-chroma (>=0.1.3,<0.2.0)
Requires-Dist: langchain-community (>=0.2.11,<0.3.0)
Requires-Dist: langchain-ollama (>=0.1.1,<0.2.0)
Requires-Dist: langchain-openai (>=0.1.22,<0.2.0)
Requires-Dist: pystow (>=0.5.4,<0.6.0)
